LICENSE
MANIFEST.in
README.md
requirements.txt
run_example.py
setup.py
docs/_build/coverage/c.txt
docs/_build/coverage/python.txt
docs/_build/dirhtml/_sources/index.txt
docs/_build/dirhtml/_sources/install.txt
docs/_build/doctest/output.txt
docs/_build/html/_sources/cli.txt
docs/_build/html/_sources/index.txt
docs/_build/html/_sources/install.txt
docs/_build/html/_sources/quickstart.txt
docs/_build/html/_sources/tuto_csv.txt
docs/_build/html/_sources/tuto_mongo.txt
docs/_build/html/_sources/tutorials.txt
examples/README.md
examples/__init__.py
examples/mongo.py
examples/sampleweibo.csv
examples/weibo.py
tests/__init__.py
tests/nonutf8sample.csv
tests/sampleweibo.csv
tests/test_corpus.py
tests/test_nlp.py
tests/test_topogram.py
tests/test_utils.py
topogram/__init__.py
topogram/corpus.py
topogram/nlp.py
topogram/old_topogram.py
topogram/topogram.py
topogram/utils.py
topogram.egg-info/PKG-INFO
topogram.egg-info/SOURCES.txt
topogram.egg-info/dependency_links.txt
topogram.egg-info/requires.txt
topogram.egg-info/top_level.txt
topogram/corpora/__init__.py
topogram/corpora/csv_file.py
topogram/corpora/elastic.py
topogram/examples/ucsv.py
topogram/languages/__init__.py
topogram/languages/zh.py
topogram/languages/dict/dict.txt.big
topogram/languages/stopwords/all.txt
topogram/languages/stopwords/zh.txt
topogram/topograms/__init__.py
topogram/topograms/basic.py
topogram/topograms/preprocess.py