Metadata-Version: 1.1
Name: topogram
Version: 0.0.7
Summary: Network Analysis
Home-page: http://topogram.io
Author: Clement Renaud
Author-email: clement.renaud@gmail.com
License: UNKNOWN
Download-URL: http://github.com/topogram/topogram
Keywords: network,visualization,NLP
Platform: UNKNOWN
Classifier: Programming Language :: Python
Classifier: Environment :: Other Environment
Classifier: Development Status :: 2 - Pre-Alpha
Classifier: Intended Audience :: Developers
Classifier: License :: OSI Approved :: GNU Library or Lesser General Public License (LGPL)
Classifier: Operating System :: OS Independent
Classifier: Topic :: Software Development :: Libraries :: Python Modules
Classifier: Topic :: Text Processing :: Linguistic
